pyharp/__init__.py
pyharp/__init__.pyi
pyharp/atm_profile.py
pyharp/compile.py
pyharp/constants.pyi
pyharp/disort.py
pyharp/klib.py
pyharp/opacity.pyi
pyharp/py.typed
pyharp/pyharp.cpython-310-x86_64-linux-gnu.so
pyharp/pyharp.pyi
pyharp/rfmlib.py
pyharp/run_cktable.py
pyharp/run_ktable_amars.py
pyharp/api/__init__.py
pyharp/api/fetch_cia_legacy.py
pyharp/api/fetch_sonora.py
pyharp/h2_cia_legacy/H2-H2-eq.orton.pt
pyharp/h2_cia_legacy/H2-H2-eq.xiz.pt
pyharp/h2_cia_legacy/H2-H2-nm.orton.pt
pyharp/h2_cia_legacy/H2-H2-nm.xiz.pt
pyharp/h2_cia_legacy/H2-He-eq.orton.pt
pyharp/h2_cia_legacy/H2-He-eq.xiz.pt
pyharp/h2_cia_legacy/H2-He-nm.orton.pt
pyharp/h2_cia_legacy/H2-He-nm.xiz.pt
pyharp/h2_cia_legacy/__init__.py
pyharp/h2_cia_legacy/h2_cia_legacy.py
pyharp/harp/CMakeLists.txt
pyharp/harp/add_arg.h
pyharp/harp/compound.cpp
pyharp/harp/compound.hpp
pyharp/harp/constants.h
pyharp/harp/element.cpp
pyharp/harp/element.hpp
pyharp/harp/harp_formatter.hpp
pyharp/harp/index.h
pyharp/harp/integrator/integrator.cpp
pyharp/harp/integrator/integrator.hpp
pyharp/harp/integrator/integrator_dispatch.cpp
pyharp/harp/integrator/integrator_dispatch.cu
pyharp/harp/integrator/integrator_formatter.hpp
pyharp/harp/integrator/radiation_model.cpp
pyharp/harp/integrator/radiation_model.hpp
pyharp/harp/math/interpn.h
pyharp/harp/math/interpolation.cpp
pyharp/harp/math/interpolation.hpp
pyharp/harp/math/locate.h
pyharp/harp/math/math_dispatch.cpp
pyharp/harp/math/trapezoid.cpp
pyharp/harp/math/trapezoid.hpp
pyharp/harp/math/tridiag.cpp
pyharp/harp/math/tridiag.hpp
pyharp/harp/opacity/atm_to_standard_grid.cpp
pyharp/harp/opacity/atm_to_standard_grid.hpp
pyharp/harp/opacity/attenuator_options.cpp
pyharp/harp/opacity/attenuator_options.hpp
pyharp/harp/opacity/fourcolumn.cpp
pyharp/harp/opacity/fourcolumn.hpp
pyharp/harp/opacity/freedman_mean.cpp
pyharp/harp/opacity/grey_cloud.cpp
pyharp/harp/opacity/grey_opacities.hpp
pyharp-1.7.8.dist-info/METADATA
pyharp-1.7.8.dist-info/WHEEL
pyharp-1.7.8.dist-info/entry_points.txt
pyharp-1.7.8.dist-info/top_level.txt
pyharp-1.7.8.dist-info/RECORD
pyharp-1.7.8.dist-info/licenses/LICENSE
