Metadata-Version: 2.4
Name: pyharp
Version: 1.7.8
Summary: High-performance Atmospheric Radiation Package
Author-email: Cheng Li <chengcli@umich.edu>
License: LICENSE
Project-URL: Homepage, https://github.com/chengcli/pyharp
Project-URL: Documentation, https://pyharp.readthedocs.io
Classifier: Development Status :: 5 - Production/Stable
Classifier: Intended Audience :: Science/Research
Classifier: Natural Language :: English
Classifier: Programming Language :: C
Classifier: Programming Language :: C++
Classifier: Programming Language :: Python :: 3.9
Classifier: Programming Language :: Python :: 3.10
Classifier: Programming Language :: Python :: 3.11
Classifier: Programming Language :: Python :: Implementation :: CPython
Classifier: Topic :: Scientific/Engineering :: Atmospheric Science
Classifier: Topic :: Scientific/Engineering :: Physics
Classifier: Topic :: Scientific/Engineering :: Astronomy
Requires-Python: >=3.9
License-File: LICENSE
Requires-Dist: numpy
Requires-Dist: pydisort>=1.3.6
Dynamic: license-file
